LICENSE
MANIFEST.in
README.md
requirements.txt
setup.py
ensemble_networkx/__init__.py
ensemble_networkx/ensemble_networkx.py
ensemble_networkx.egg-info/PKG-INFO
ensemble_networkx.egg-info/SOURCES.txt
ensemble_networkx.egg-info/dependency_links.txt
ensemble_networkx.egg-info/requires.txt
ensemble_networkx.egg-info/top_level.txt
ensemble_networkx/.ipynb_checkpoints/__init__-checkpoint.py
ensemble_networkx/.ipynb_checkpoints/ensemble_networkx-checkpoint.py